carmd/__init__.py
carmd/carmd.py
python_carmd-0.2.0.dist-info/LICENSE
python_carmd-0.2.0.dist-info/METADATA
python_carmd-0.2.0.dist-info/WHEEL
python_carmd-0.2.0.dist-info/top_level.txt
python_carmd-0.2.0.dist-info/RECORD
